odoo/addons/website_recaptcha_v2/README.rst
odoo/addons/website_recaptcha_v2/__init__.py
odoo/addons/website_recaptcha_v2/__manifest__.py
odoo/addons/website_recaptcha_v2/demo/demo.xml
odoo/addons/website_recaptcha_v2/i18n/it.po
odoo/addons/website_recaptcha_v2/i18n/website_recaptcha_v2.pot
odoo/addons/website_recaptcha_v2/models/__init__.py
odoo/addons/website_recaptcha_v2/models/res_config_settings.py
odoo/addons/website_recaptcha_v2/models/website.py
odoo/addons/website_recaptcha_v2/readme/CONFIGURE.rst
odoo/addons/website_recaptcha_v2/readme/CONTRIBUTORS.rst
odoo/addons/website_recaptcha_v2/readme/DESCRIPTION.rst
odoo/addons/website_recaptcha_v2/static/description/icon.png
odoo/addons/website_recaptcha_v2/static/description/index.html
odoo/addons/website_recaptcha_v2/static/description/recaptcha_ico.png
odoo/addons/website_recaptcha_v2/tests/__init__.py
odoo/addons/website_recaptcha_v2/tests/test_recaptcha.py
odoo/addons/website_recaptcha_v2/views/res_config_settings_view.xml
odoo/addons/website_recaptcha_v2/views/website_templates.xml
odoo_addon_website_recaptcha_v2-16.0.1.0.0.5.dist-info/METADATA
odoo_addon_website_recaptcha_v2-16.0.1.0.0.5.dist-info/WHEEL
odoo_addon_website_recaptcha_v2-16.0.1.0.0.5.dist-info/top_level.txt
odoo_addon_website_recaptcha_v2-16.0.1.0.0.5.dist-info/RECORD
